fiftyone_pipeline_engines/__init__.py
fiftyone_pipeline_engines/aspectdata.py
fiftyone_pipeline_engines/aspectdata_dictionary.py
fiftyone_pipeline_engines/basic_dictionary_cache.py
fiftyone_pipeline_engines/datafile.py
fiftyone_pipeline_engines/datafile_update_service.py
fiftyone_pipeline_engines/datakeyed_cache.py
fiftyone_pipeline_engines/engine.py
fiftyone_pipeline_engines/lru_cache.py
fiftyone_pipeline_engines/missingproperty_service.py
fiftyone_pipeline_engines/tracker.py
fiftyone_pipeline_engines-4.5.3.dist-info/METADATA
fiftyone_pipeline_engines-4.5.3.dist-info/WHEEL
fiftyone_pipeline_engines-4.5.3.dist-info/top_level.txt
fiftyone_pipeline_engines-4.5.3.dist-info/RECORD
